dataplate/__init__.py
dataplate/client.py
dataplate-1.0.1.dist-info/Icon
dataplate-1.0.1.dist-info/METADATA
dataplate-1.0.1.dist-info/WHEEL
dataplate-1.0.1.dist-info/top_level.txt
dataplate-1.0.1.dist-info/RECORD
