Metadata-Version: 2.1
Name: dataplate
Version: 1.0.1
Summary: DataPlate Python API - interact with Dataplate webserver
Home-page: https://github.com/Dataplate/dataplate
Author: DataPlate team
Author-email: info@dataplate.io
License: Apache 2.0
Classifier: Programming Language :: Python :: 3
Classifier: License :: OSI Approved :: Apache Software License
Classifier: Operating System :: OS Independent
Classifier: Programming Language :: Python
Classifier: Programming Language :: Python :: 3.6
Classifier: Programming Language :: Python :: 3.7
Classifier: Programming Language :: Python :: 3.8
Requires-Python: >=3.6
Requires-Dist: boto3 (>=1.9.235)
Requires-Dist: awswrangler (>=2.0.0)
Requires-Dist: requests
Requires-Dist: scrapbook
